resolwe_runtime_utils.py
resolwe_runtime_utils-3.4.0.dist-info/AUTHORS
resolwe_runtime_utils-3.4.0.dist-info/LICENSE
resolwe_runtime_utils-3.4.0.dist-info/METADATA
resolwe_runtime_utils-3.4.0.dist-info/WHEEL
resolwe_runtime_utils-3.4.0.dist-info/entry_points.txt
resolwe_runtime_utils-3.4.0.dist-info/top_level.txt
resolwe_runtime_utils-3.4.0.dist-info/RECORD
