Metadata-Version: 2.1
Name: resolwe-runtime-utils
Version: 3.4.0
Summary: Runtime utilities for Resolwe dataflow engine
Home-page: https://github.com/genialis/resolwe-runtime-utils
Author: Genialis, Inc.
Author-email: dev-team@genialis.com
License: Apache License (2.0)
Keywords: resolwe runtime utilities library
Classifier: Development Status :: 4 - Beta
Classifier: Environment :: Console
Classifier: Intended Audience :: Developers
Classifier: Topic :: Software Development :: Libraries
Classifier: Topic :: Utilities
Classifier: License :: OSI Approved :: Apache Software License
Classifier: Operating System :: OS Independent
Classifier: Programming Language :: Python :: 3
Classifier: Programming Language :: Python :: 3.8
Classifier: Programming Language :: Python :: 3.9
Classifier: Programming Language :: Python :: 3.10
Classifier: Programming Language :: Python :: 3.11
Classifier: Programming Language :: Python :: 3.12
License-File: LICENSE
License-File: AUTHORS
Requires-Dist: requests ~=2.32.3
Provides-Extra: dev
Requires-Dist: tox ; extra == 'dev'
Provides-Extra: docs
Requires-Dist: Sphinx ; extra == 'docs'
Requires-Dist: sphinx-rtd-theme ; extra == 'docs'
Provides-Extra: package
Requires-Dist: twine ; extra == 'package'
Requires-Dist: wheel ; extra == 'package'
Provides-Extra: test
Requires-Dist: black ; extra == 'test'
Requires-Dist: check-manifest ; extra == 'test'
Requires-Dist: readme ; extra == 'test'
Requires-Dist: pytest-cov ; extra == 'test'
Requires-Dist: responses ; extra == 'test'
Requires-Dist: setuptools >=56.0.0 ; extra == 'test'
Requires-Dist: setuptools-scm ; extra == 'test'
